suntzu/__init__.py
suntzu/cleaning.py
suntzu/errors.py
suntzu/getter.py
suntzu/statistics.py
suntzu/suntzu.py
suntzu/utils.py
suntzu-1.0.1.dist-info/METADATA
suntzu-1.0.1.dist-info/WHEEL
suntzu-1.0.1.dist-info/licenses/LICENSE
suntzu-1.0.1.dist-info/RECORD
