Metadata-Version: 2.4
Name: Suntzu
Version: 1.0.1
Summary: Data Science Library that makes simple data analysis tasks
License-File: LICENSE
Author: Igor Carvalheira
Author-email: igorccarvalheira111@gmail.com
Requires-Python: >=3.10
Classifier: Programming Language :: Python :: 3
Classifier: Programming Language :: Python :: 3.10
Classifier: Programming Language :: Python :: 3.11
Classifier: Programming Language :: Python :: 3.12
Classifier: Programming Language :: Python :: 3.13
Classifier: Programming Language :: Python :: 3.14
Requires-Dist: ipython
Requires-Dist: numpy
Requires-Dist: pandas
